[{"auteur":"gonxped31","nom":"Ceuillir en l'air","dateDebut":1690776000000,"dateFin":1690862400000,"listeDeTache":[{"nom":"Survoler","taches":[{"nomAction":"Voler","composantes":["CPU","ROUE","HELICE","BRAS","MICRO"],"duree":"150"},{"nomAction":"Avancer","composantes":["CPU","ROUE"],"duree":"60"}],"dureeTache":210},{"nom":"Ceuillette","taches":[{"nomAction":"Prendre","composantes":["CPU","BRAS"],"duree":"30"},{"nomAction":"Avancer","composantes":["CPU","ROUE"],"duree":"60"}],"dureeTache":90}],"listeInteretAssocie":[{"nom":""}],"listeUtilisateurInsccrit":["gonxped31"],"points":29,"dureeActivite":300,"listeRobotsInscrits":[{"nom":"Bobby","vitesse":0,"batterie":98,"cpu":46,"memoire":84.0,"composantes":[{"nom":"cpu","prix":"150000","description":"Description cpu","typeComposant":"CPU"},{"nom":"bras","prix":"800000","description":"Description bras","typeComposant":"BRAS"},{"nom":"roue","prix":"570000","description":"Description roue","typeComposant":"ROUE"},{"nom":"helice","prix":"457000","description":"Description helice","typeComposant":"HELICE"},{"nom":"micro","prix":"365000000","description":"Description micro","typeComposant":"MICRO"},{"nom":"hautparleur","prix":"7540000","description":"Description hautparleur","typeComposant":"HAUTPARLEUR"},{"nom":"ecran","prix":"841000000","description":"Description ecran","typeComposant":"ECRAN"},{"nom":"cpu","prix":"150000","description":"Description cpu","typeComposant":"CPU"}],"type":"Type1","taches":[{"nom":"Survoler","taches":[{"nomAction":"Voler","composantes":["CPU","ROUE","HELICE","BRAS","MICRO"],"duree":"150"},{"nomAction":"Avancer","composantes":["CPU","ROUE"],"duree":"60"}],"dureeTache":210},{"nom":"Ceuillette","taches":[{"nomAction":"Prendre","composantes":["CPU","BRAS"],"duree":"30"},{"nomAction":"Avancer","composantes":["CPU","ROUE"],"duree":"60"}],"dureeTache":90}],"activites":[],"actions":[],"numeroSerie":"5aa4ffcf-4647-4840-8115-3cc6f5975d7d","y":0,"x":0,"numero":7}]},{"auteur":"KD","nom":"Ballade aerienne","dateDebut":1690776000000,"dateFin":1691208000000,"listeDeTache":[{"nom":"Prendre en l'air","taches":[{"nomAction":"Prendre","composantes":["CPU","BRAS"],"duree":"15"},{"nomAction":"Voler","composantes":["CPU","ROUE","HELICE","BRAS"],"duree":"50"}],"dureeTache":65}],"listeInteretAssocie":[{"nom":"Explorer"}],"listeUtilisateurInsccrit":[],"points":23,"dureeActivite":65,"listeRobotsInscrits":[]},{"auteur":"gonxped31","nom":"Cascade aerienne","dateDebut":1690948800000,"dateFin":1691380800000,"listeDeTache":[{"nom":"Survoler","taches":[{"nomAction":"Voler","composantes":["CPU","ROUE","HELICE","BRAS","MICRO"],"duree":"150"},{"nomAction":"Avancer","composantes":["CPU","ROUE"],"duree":"60"}],"dureeTache":210}],"listeInteretAssocie":[{"nom":"Explorer"}],"listeUtilisateurInsccrit":["gonxped31","KD"],"points":20,"dureeActivite":210,"listeRobotsInscrits":[{"nom":"Bobby","vitesse":0,"batterie":100,"cpu":120,"memoire":32.0,"composantes":[{"nom":"cpu","prix":"150000","description":"Description cpu","typeComposant":"CPU"},{"nom":"bras","prix":"800000","description":"Description bras","typeComposant":"BRAS"},{"nom":"roue","prix":"570000","description":"Description roue","typeComposant":"ROUE"},{"nom":"helice","prix":"457000","description":"Description helice","typeComposant":"HELICE"},{"nom":"micro","prix":"365000000","description":"Description micro","typeComposant":"MICRO"},{"nom":"hautparleur","prix":"7540000","description":"Description hautparleur","typeComposant":"HAUTPARLEUR"},{"nom":"ecran","prix":"841000000","description":"Description ecran","typeComposant":"ECRAN"},{"nom":"cpu","prix":"150000","description":"Description cpu","typeComposant":"CPU"},{"nom":"cpu","prix":"150000","description":"Description cpu","typeComposant":"CPU"}],"type":"Type1","taches":[{"nom":"Prendre en l'air","taches":[{"nomAction":"Prendre","composantes":["CPU","BRAS"],"duree":"15"},{"nomAction":"Voler","composantes":["CPU","ROUE","HELICE","BRAS"],"duree":"50"}],"dureeTache":65}],"activites":["Cascade aerienne"],"actions":[],"numeroSerie":"781cb5b8-61e7-4bac-949e-5f5d0c10ddab","y":0,"x":0,"numero":7}]}]